Metadata-Version: 2.4
Name: context-portal-mcp-fastmcp
Version: 0.3.5
Summary: A Model Context Protocol (MCP) server for managing structured project context.
Author-email: Scott McLeod <contextportal@gmail.com>
License: Apache-2.0
Project-URL: Homepage, https://github.com/fastmcp-me/context-portal#readme
Project-URL: Repository, https://github.com/fastmcp-me/context-portal.git
Project-URL: Issues, https://github.com/fastmcp-me/context-portal/issues
Keywords: mcp,context,portal,fastapi,server
Classifier: Programming Language :: Python :: 3
Classifier: Programming Language :: Python :: 3.10
Classifier: Programming Language :: Python :: 3.11
Classifier: Programming Language :: Python :: 3.12
Classifier: Programming Language :: Python :: 3.13
Classifier: License :: OSI Approved :: Apache Software License
Classifier: Operating System :: OS Independent
Classifier: Development Status :: 4 - Beta
Classifier: Intended Audience :: Developers
Classifier: Topic :: Software Development :: Libraries :: Python Modules
Requires-Python: >=3.10
License-File: LICENSE
Requires-Dist: fastapi==0.116.2
Requires-Dist: starlette<0.49.0,>=0.47.2
Requires-Dist: uvicorn[standard]
Requires-Dist: pydantic>=2.0.0
Requires-Dist: fastmcp>=0.9.0
Requires-Dist: sentence-transformers
Requires-Dist: chromadb>=1.0.0
Requires-Dist: alembic
Provides-Extra: dev
Requires-Dist: pytest>=7.0.0; extra == "dev"
Requires-Dist: pytest-asyncio; extra == "dev"
Requires-Dist: black; extra == "dev"
Requires-Dist: isort; extra == "dev"
Requires-Dist: flake8; extra == "dev"
Requires-Dist: mypy; extra == "dev"
Provides-Extra: test
Requires-Dist: pytest>=7.0.0; extra == "test"
Requires-Dist: pytest-asyncio; extra == "test"
Requires-Dist: pytest-cov; extra == "test"
Dynamic: license-file
